{"name":"t:sections.footer.name","type":"footer","sections":{"custom_liquid_KXMeip":{"type":"custom-liquid","settings":{"custom_liquid":"<style>\n.flex-container {\ndisplay: flex;\nflex-flow: wrap;\njustify-content: space-around;\npadding-left: 1.2rem;\n\n}\n.flex-container > div {\n  width: 24%;\n  min-width: 350px;\n  max-width: 350px;  \n  left: 0px;\n  margin: 0px;\n  line-height: 26px;\n  font-size: 13px;\n  text-align: left;\n  color: #000;\n}\na.A1 {\ncolor: #000;\nline-height: 40px;\n}\n\na.A2 {\ncolor: #000;\nline-height: 30px;\ntext-decoration: none;\n}\na.A2:hover {\ntext-decoration: underline;\n}\n.footer-A1 p {\n}\n.footer-A2 a {\ncolor: #000;\nline-height: 30px;\ntext-decoration: none;\n\n\n}\n<\/style>\n\n<div class=\"flex-container\">\n  <div><p class=\"footer-A1\"><h4>CARE<\/h4>A Sandgrens expert is available at 1-800-245-0187, (Mon-Fri) between 0900-1600 CST. <br>You can also <a class=\"A1\" href=\"#\">chat<\/a> or <a class=\"A1\"  href=\"mailto:care@sandgrens.com\">email us<\/a>.<\/p>\n<p class=\"footer-A2\"><a class=\"A2\" href=\"https:\/\/sandgrens.com\/pages\/faq\">FAQ<\/a><br>\n<a class=\"A2\"  href=\"https:\/\/sandgrens.com\/pages\/shipping\">Shipping<\/a><br>\n<a class=\"A2\" href=\"https:\/\/sandgrens.com\/pages\/return-exchanges\">Returns & Exchanges<\/a><br>\n<a class=\"A2\" href=\"https:\/\/sandgrens.com\/pages\/sizing-and-fit\">Sizing & Fit<\/a><br>\n<a class=\"A2\" href=\"https:\/\/sandgrens.com\/collections\/product-care\">Product Care<\/a><\/p>\n<\/div>\n  <div>\n<h4>ABOUT SANDGRENS<\/h4>\n<a class=\"A2\" href=\"https:\/\/sandgrens.com\/pages\/sustainability\">Sustainability<\/a><br>\n<a class=\"A2\" href=\"https:\/\/sandgrens.com\/pages\/press\">Press<\/a><br>\n<a class=\"A2\" href=\"https:\/\/sandgrens.com\/blogs\/blog\">Blog<\/a><br>\n<a class=\"A2\" href=\"https:\/\/sandgrens.com\/pages\/wholesale\">Wholesale<\/a><br>\n<\/div>\n<div>\n<h4>CONNECT<\/h4>\n<a class=\"A2\" href=\"https:\/\/www.instagram.com\/sandgrensofficial\/\" target=\"_blank\">Instagram<\/a><br>\n<a class=\"A2\" href=\"https:\/\/www.facebook.com\/sandgrensofficial\" target=\"_blank\">Facebook<\/a><br>\n<a class=\"A2\" href=\"https:\/\/www.pinterest.se\/sandgrens\/\" target=\"_blank\">Pinterest<\/a><br>\n<a class=\"A2\" href=\"https:\/\/www.tiktok.com\/@sandgrens\" target=\"_blank\">TikTok<\/a><br>\n<a class=\"A2\" href=\"https:\/\/www.youtube.com\/@sandgrensclogs8179\" target=\"_blank\">YouTube<\/a>\n<\/div>  \n  <div>\n<h4>LEGAL<\/h4>\n<a class=\"A2\" href=\"https:\/\/sandgrens.com\/pages\/privacy-policy\">Privacy Policy<\/a><br>\n<a class=\"A2\" href=\"https:\/\/sandgrens.com\/pages\/cookie-policy\">Cookie Policy<\/a>\n<br>\n<a class=\"A2\" href=\"https:\/\/sandgrens.com\/pages\/terms-and-conditions\">Terms and Conditions<\/a><br>\n<a class=\"A2\" href=\"https:\/\/sandgrens.com\/pages\/accessibility\">Accessibility<\/a><br>\n<a class=\"A2\" href=\"https:\/\/sandgrens.com\/pages\/ccpa-opt-out\">Do not sell my personal information<\/a><\/div>\n\n<\/div>","color_scheme":"","padding_top":40,"padding_bottom":52}},"custom_liquid_ywetxY":{"type":"custom-liquid","settings":{"custom_liquid":"<center>\n<img src=\"https:\/\/cdn.shopify.com\/s\/files\/1\/0762\/2777\/2735\/files\/sandgrens-owl.png?v=1699928468\" alt=\"Sandgrens Owl of Wisdom\" \/> \n<br>\n<p style=\"font-size:12px\"> © 2024, Sandgrens, LLC <\/p>\n<\/center>","color_scheme":"","padding_top":40,"padding_bottom":52}},"footer":{"type":"footer","blocks":{"link_list_yQEBPC":{"type":"link_list","settings":{"heading":"","menu":"footer-1"}},"link_list_7gXR9H":{"type":"link_list","settings":{"heading":"","menu":"footer-2"}},"link_list_BmH7dK":{"type":"link_list","settings":{"heading":"","menu":"footer-3"}},"link_list_mArPxB":{"type":"link_list","settings":{"heading":"","menu":"footer-4"}}},"block_order":["link_list_yQEBPC","link_list_7gXR9H","link_list_BmH7dK","link_list_mArPxB"],"disabled":true,"custom_css":[],"settings":{"color_scheme":"background-1","newsletter_enable":false,"newsletter_heading":"Subscribe to our emails","enable_follow_on_shop":false,"show_social":true,"enable_country_selector":true,"enable_language_selector":true,"payment_enable":true,"show_policy":false,"margin_top":36,"padding_top":36,"padding_bottom":36}}},"order":["custom_liquid_KXMeip","custom_liquid_ywetxY","footer"]}